flask_exception/__init__.py
flask_exception/_version.py
flask_exception/flask_exception.py
flask_exception-0.0.1.dist-info/AUTHORS.md
flask_exception-0.0.1.dist-info/METADATA
flask_exception-0.0.1.dist-info/WHEEL
flask_exception-0.0.1.dist-info/top_level.txt
flask_exception-0.0.1.dist-info/RECORD
