Metadata-Version: 2.1
Name: flask-exception
Version: 0.0.1
Summary: Flask-Exception is a Flask extension that provides exception handling and logging for Flask applications.
Author-email: Ido Shraga <idoshraga@gmail.com>
License: BSD 3-Clause License
Project-URL: Homepage, https://github.com/idoshr/flask-exception
Project-URL: Documentation, https://flask-exception.readthedocs.io/en/latest/
Project-URL: Repository, https://github.com/idoshr/flask-exception
Project-URL: Changelog, https://github.com/idoshr/flask-exception/releases
Keywords: flask,exception,extension
Platform: any
Classifier: Development Status :: 4 - Beta
Classifier: Environment :: Web Environment
Classifier: Intended Audience :: Developers
Classifier: License :: OSI Approved :: BSD License
Classifier: Operating System :: OS Independent
Classifier: Programming Language :: Python
Classifier: Programming Language :: Python :: 3 :: Only
Classifier: Programming Language :: Python :: 3
Classifier: Programming Language :: Python :: 3.8
Classifier: Programming Language :: Python :: 3.9
Classifier: Programming Language :: Python :: 3.10
Classifier: Programming Language :: Python :: 3.11
Classifier: Programming Language :: Python :: Implementation :: PyPy
Classifier: Programming Language :: Python :: Implementation :: CPython
Classifier: Topic :: Internet :: WWW/HTTP :: Dynamic Content
Classifier: Topic :: Software Development :: Libraries :: Python Modules
Classifier: Framework :: Flask
Requires-Python: >=3.8
License-File: AUTHORS.md
Requires-Dist: Flask >=1.1.4
